skey/__init__.py
skey/core.py
skey_lib-0.2.0.dist-info/METADATA
skey_lib-0.2.0.dist-info/WHEEL
skey_lib-0.2.0.dist-info/top_level.txt
skey_lib-0.2.0.dist-info/RECORD
